{"_ts":[1496296742,1496384528],"_r":{"breakdown":{"html":{"bytes":[118244,113811],"requests":[34,24]},"js":{"bytes":[760597,746571],"requests":[73,76]},"css":{"bytes":[118058,116346],"requests":[6,4]},"image":{"bytes":[2906547,3438504],"requests":[99,90]},"flash":{"bytes":[0,0],"requests":[0,0]},"font":{"bytes":[23256,5942],"requests":[2,1]},"other":{"bytes":[1009,1009],"requests":[2,2]}},"date":[1496296742,1496384528],"domElements":[2975,2921],"domInteractive":[10916,9953],"firstPaint":[1879,1827],"fullyLoaded":[18662,17398],"id":["170601_0Z_BAW","170602_6Z_D7B"],"loadTime":[18285,17027],"render":[2052,1948],"SpeedIndex":[11568,12371],"TTFB":[415,439],"videoFrames":[[{"_i":"frame_0000.jpg","_t":0,"_vc":0},{"_i":"frame_0021.jpg","_t":2100,"_vc":5},{"_i":"frame_0032.jpg","_t":3200,"_vc":5},{"_i":"frame_0041.jpg","_t":4100,"_vc":11},{"_i":"frame_0059.jpg","_t":5900,"_vc":32},{"_i":"frame_0067.jpg","_t":6700,"_vc":28},{"_i":"frame_0109.jpg","_t":10900,"_vc":28},{"_i":"frame_0139.jpg","_t":13900,"_vc":83},{"_i":"frame_0153.jpg","_t":15300,"_vc":100}],[{"_i":"frame_0000.jpg","_t":0,"_vc":0},{"_i":"frame_0019.jpg","_t":1900,"_vc":5},{"_i":"frame_0031.jpg","_t":3100,"_vc":5},{"_i":"frame_0032.jpg","_t":3200,"_vc":5},{"_i":"frame_0044.jpg","_t":4400,"_vc":5},{"_i":"frame_0058.jpg","_t":5800,"_vc":18},{"_i":"frame_0103.jpg","_t":10300,"_vc":18},{"_i":"frame_0137.jpg","_t":13700,"_vc":84},{"_i":"frame_0155.jpg","_t":15500,"_vc":100}]],"visualComplete":[15300,15500],"lighthouse":[null,null],"pagespeed":[36,36]}}